README.md
setup.py
dateobjects/__init__.py
dateobjects/dateobjects.py
dateobjects/delta.py
dateobjects/utils.py
dateobjects.egg-info/PKG-INFO
dateobjects.egg-info/SOURCES.txt
dateobjects.egg-info/dependency_links.txt
dateobjects.egg-info/not-zip-safe
dateobjects.egg-info/top_level.txt