Metadata-Version: 1.1
Name: dateobjects
Version: 2.0.0
Summary: dateobjects is a helper to manipulate dates.
Home-page: https://github.com/zokis/DateObjects/
Author: Marcelo Fonseca Tambalo
Author-email: marcelo.zokis@gmail.com
License: WTFL
Platform: any
Classifier: Development Status :: 5 - Production/Stable
Classifier: Intended Audience :: Developers
Classifier: Operating System :: OS Independent
Classifier: Programming Language :: Python
Classifier: Programming Language :: Python :: 3
Classifier: Programming Language :: Python :: 3.7
Classifier: Topic :: Software Development :: Libraries :: Python Modules
